{"google":"","note":"Don't delete this file! It's used internally to help with page regeneration.","body":"CNUThesis\r\n=========\r\n\r\nLaTeX Thesis Template for Capital Normal University\r\n\r\n首都师范大学学位论文 LaTeX 模板\r\n\r\n-------------\r\n\r\n简介\r\n-------------\r\nCNUThesis 宏包是根据首都师范大学本科生毕业设计(论文)格式要求以及首都师范大学硕士(博士)学位论文格式要求编写的。宏包旨在为首都师范大学的学生提供一个简单、专业、有效的排版工具以简化学位论文的撰写，使得论文作者可以将精力集中到论文的内容上而不是浪费在版面设置上。同时宏包在符合学位论文撰写要求的基础上尽可能地进行美化，其中还参考了出版界的一些排版规范。\r\n\r\nCNUThesis 使用 XeLaTeX，方便字体设置。中文支持使用xeCJK包。\r\n\r\n为了便于开发和维护，研究生、博士生的LaTeX 模板与本科生的学位论文模板分别独立开发。现在已经支持硕士/博士学位论文格式，本科论文格式即将支持，敬请期待。\r\n\r\n模板生成的论文效果以及模板使用手册请见相应目录下的PDF格式文档。\r\n\r\n本项目正在开发中，欢迎首都师范大学的同学加入进来。同时，如果你有什么好的建议，欢迎联系我(Email:imengyingchina@gmail.com)。\r\n\r\n致谢\r\n-------------\r\n该模板是在华南师范大学的[SCNUThesis](https://code.google.com/p/scnuthesis/)的基础上完成的，修改了封面、页脚等使之符合学校的论文要求。\r\n\r\n在制作模板的过程中也参考了国防科技大学的 NUDTpaper、清华的 Thuthesis、中科院计算所 ICTthesis、\r\n中国科学技术大学 USTCthesis 等硕博论文模板,一并表示感谢。\r\n","name":"CNUThesis","tagline":"LaTeX Thesis Template for Capital Normal University"}